{"ok":true,"data":"2026-06-21","data_de":"2026-06-21","data_ate":"2026-06-21","total":76,"dados":[{"_row":32092,"data":"21/06/2026","maquina":"MAQUINA 01","linha":"803","work_id":"38030301","carro":"1164","motorista":"13003","preparo":"12:03","horario_de_saida_da_garagem":"12:13","saida_real":"12:11","saiu_no_horaro":"SIM","minutos_atrasado_garagem":"","minutos_adiantado_garagem":"","saida_atrasado_adiantado":"NO HORÁRIO","local_inicio":"TVX-V.XAVIER","trajeto_ocioso_correto":"NÃO","horario_de_inicio":"12:33","inicio_real":"12:34","inicio_no_horario":"NO HORÁRIO","observacoes":"","minutos_atrasado_no_inicio":"","minutos_adiantado_no_inicio":"","horario_saida_da_garagem":"12:13","saiu_no_horario":"SIM","data_iso":"2026-06-21"},{"_row":32091,"data":"21/06/2026","maquina":"MAQUINA 01","linha":"803","work_id":"38030201","carro":"1159","motorista":"13104","preparo":"11:33","horario_de_saida_da_garagem":"11:43","saida_real":"11:46","saiu_no_horaro":"SIM","minutos_atrasado_garagem":"","minutos_adiantado_garagem":"","saida_atrasado_adiantado":"NO HORÁRIO","local_inicio":"TVX-V.XAVIER","trajeto_ocioso_correto":"SIM","horario_de_inicio":"12:03","inicio_real":"12:05","inicio_no_horario":"NO HORÁRIO","observacoes":"","minutos_atrasado_no_inicio":"","minutos_adiantado_no_inicio":"","horario_saida_da_garagem":"11:43","saiu_no_horario":"SIM","data_iso":"2026-06-21"},{"_row":32090,"data":"21/06/2026","maquina":"MAQUINA 01","linha":"803","work_id":"38030101","carro":"1156","motorista":"12690","preparo":"11:03","horario_de_saida_da_garagem":"11:13","saida_real":"","saiu_no_horaro":"","minutos_atrasado_garagem":"","minutos_adiantado_garagem":"","saida_atrasado_adiantado":"","local_inicio":"TVX-V.XAVIER","trajeto_ocioso_correto":"","horario_de_inicio":"11:33","inicio_real":"","inicio_no_horario":"","observacoes":"","minutos_atrasado_no_inicio":"","minutos_adiantado_no_inicio":"","horario_saida_da_garagem":"11:13","data_iso":"2026-06-21"},{"_row":32089,"data":"21/06/2026","maquina":"MAQUINA 01","linha":"113","work_id":"31130101","carro":"3115","motorista":"9630","preparo":"10:20","horario_de_saida_da_garagem":"10:30","saida_real":"","saiu_no_horaro":"","minutos_atrasado_garagem":"","minutos_adiantado_garagem":"15","saida_atrasado_adiantado":"ADIANTADO","local_inicio":"TCS-T.C SUP.","trajeto_ocioso_correto":"NÃO","horario_de_inicio":"10:45","inicio_real":"10:45","inicio_no_horario":"NO HORÁRIO","observacoes":"carro saiu do PI","minutos_atrasado_no_inicio":"","minutos_adiantado_no_inicio":"","horario_saida_da_garagem":"10:30","data_iso":"2026-06-21"},{"_row":32088,"data":"21/06/2026","maquina":"MAQUINA 01","linha":"900","work_id":"39000301","carro":"1154","motorista":"11021","preparo":"09:24","horario_de_saida_da_garagem":"09:34","saida_real":"09:32","saiu_no_horaro":"SIM","minutos_atrasado_garagem":"","minutos_adiantado_garagem":"","saida_atrasado_adiantado":"NO HORÁRIO","local_inicio":"TVX-V.XAVIER","trajeto_ocioso_correto":"SIM","horario_de_inicio":"09:54","inicio_real":"09:54","inicio_no_horario":"NO HORÁRIO","observacoes":"","minutos_atrasado_no_inicio":"","minutos_adiantado_no_inicio":"","horario_saida_da_garagem":"09:34","saiu_no_horario":"SIM","data_iso":"2026-06-21"},{"_row":32087,"data":"21/06/2026","maquina":"MAQUINA 01","linha":"900","work_id":"39000201","carro":"-","motorista":"","preparo":"08:54","horario_de_saida_da_garagem":"09:04","saida_real":"09:10","saiu_no_horaro":"NÃO","minutos_atrasado_garagem":"","minutos_adiantado_garagem":"","saida_atrasado_adiantado":"","local_inicio":"TVX-V.XAVIER","trajeto_ocioso_correto":"","horario_de_inicio":"09:24","inicio_real":"","inicio_no_horario":"","observacoes":"","minutos_atrasado_no_inicio":"","minutos_adiantado_no_inicio":"","horario_saida_da_garagem":"09:04","saiu_no_horario":"NÃO","data_iso":"2026-06-21"},{"_row":32086,"data":"21/06/2026","maquina":"MAQUINA 01","linha":"900","work_id":"39000101","carro":"1151","motorista":"13146","preparo":"08:24","horario_de_saida_da_garagem":"08:34","saida_real":"08:34","saiu_no_horaro":"SIM","minutos_atrasado_garagem":"","minutos_adiantado_garagem":"","saida_atrasado_adiantado":"NO HORÁRIO","local_inicio":"TVX-V.XAVIER","trajeto_ocioso_correto":"NÃO","horario_de_inicio":"08:54","inicio_real":"08:57","inicio_no_horario":"NO HORÁRIO","observacoes":"","minutos_atrasado_no_inicio":"","minutos_adiantado_no_inicio":"","horario_saida_da_garagem":"08:34","saiu_no_horario":"SIM","data_iso":"2026-06-21"},{"_row":32085,"data":"21/06/2026","maquina":"MAQUINA 01","linha":"110","work_id":"31100201","carro":"3177","motorista":"11932","preparo":"05:58","horario_de_saida_da_garagem":"06:08","saida_real":"06:08","saiu_no_horaro":"SIM","minutos_atrasado_garagem":"","minutos_adiantado_garagem":"","saida_atrasado_adiantado":"NO HORÁRIO","local_inicio":"TCS-T.C SUP.","trajeto_ocioso_correto":"SIM","horario_de_inicio":"06:23","inicio_real":"06:24","inicio_no_horario":"NO HORÁRIO","observacoes":"","minutos_atrasado_no_inicio":"","minutos_adiantado_no_inicio":"","horario_saida_da_garagem":"06:08","saiu_no_horario":"SIM","data_iso":"2026-06-21"},{"_row":32084,"data":"21/06/2026","maquina":"MAQUINA 01","linha":"449","work_id":"34490301","carro":"4604","motorista":"12499","preparo":"05:50","horario_de_saida_da_garagem":"06:00","saida_real":"05:55","saiu_no_horaro":"SIM","minutos_atrasado_garagem":"","minutos_adiantado_garagem":"","saida_atrasado_adiantado":"NO HORÁRIO","local_inicio":"TMG-T.M.GAV","trajeto_ocioso_correto":"SIM","horario_de_inicio":"06:10","inicio_real":"06:09","inicio_no_horario":"NO HORÁRIO","observacoes":"","minutos_atrasado_no_inicio":"","minutos_adiantado_no_inicio":"30/12/1899","horario_saida_da_garagem":"06:00","saiu_no_horario":"SIM","data_iso":"2026-06-21"},{"_row":32083,"data":"21/06/2026","maquina":"MAQUINA 01","linha":"100","work_id":"31000101","carro":"3121","motorista":"9630","preparo":"05:50","horario_de_saida_da_garagem":"06:00","saida_real":"06:02","saiu_no_horaro":"SIM","minutos_atrasado_garagem":"","minutos_adiantado_garagem":"","saida_atrasado_adiantado":"NO HORÁRIO","local_inicio":"TCI-T.C INF.","trajeto_ocioso_correto":"NÃO","horario_de_inicio":"06:10","inicio_real":"06:16","inicio_no_horario":"ATRASADO","observacoes":"","minutos_atrasado_no_inicio":"00:06","minutos_adiantado_no_inicio":"","horario_saida_da_garagem":"06:00","saiu_no_horario":"SIM","data_iso":"2026-06-21"},{"_row":32082,"data":"21/06/2026","maquina":"MAQUINA 01","linha":"501","work_id":"35010301","carro":"3172","motorista":"9884","preparo":"05:38","horario_de_saida_da_garagem":"05:48","saida_real":"05:47","saiu_no_horaro":"SIM","minutos_atrasado_garagem":"","minutos_adiantado_garagem":"","saida_atrasado_adiantado":"NO HORÁRIO","local_inicio":"BAIRRO","trajeto_ocioso_correto":"SIM","horario_de_inicio":"06:03","inicio_real":"06:01","inicio_no_horario":"ADIANTADO","observacoes":"","minutos_atrasado_no_inicio":"","minutos_adiantado_no_inicio":"00:01","horario_saida_da_garagem":"05:48","saiu_no_horario":"SIM","data_iso":"2026-06-21"},{"_row":32081,"data":"21/06/2026","maquina":"MAQUINA 01","linha":"314","work_id":"33140301","carro":"3161","motorista":"7996","preparo":"05:37","horario_de_saida_da_garagem":"05:47","saida_real":"05:50","saiu_no_horaro":"SIM","minutos_atrasado_garagem":"","minutos_adiantado_garagem":"","saida_atrasado_adiantado":"NO HORÁRIO","local_inicio":"BAIRRO","trajeto_ocioso_correto":"SIM","horario_de_inicio":"06:02","inicio_real":"06:09","inicio_no_horario":"ATRASADO","observacoes":"","minutos_atrasado_no_inicio":"00:07","minutos_adiantado_no_inicio":"","horario_saida_da_garagem":"05:47","saiu_no_horario":"SIM","data_iso":"2026-06-21"},{"_row":32080,"data":"21/06/2026","maquina":"MAQUINA 01","linha":"425","work_id":"34250201","carro":"3146","motorista":"10862","preparo":"05:35","horario_de_saida_da_garagem":"05:45","saida_real":"05:46","saiu_no_horaro":"SIM","minutos_atrasado_garagem":"","minutos_adiantado_garagem":"","saida_atrasado_adiantado":"NO HORÁRIO","local_inicio":"BAIRRO","trajeto_ocioso_correto":"SIM","horario_de_inicio":"05:55","inicio_real":"06:05","inicio_no_horario":"ATRASADO","observacoes":"","minutos_atrasado_no_inicio":"00:10","minutos_adiantado_no_inicio":"","horario_saida_da_garagem":"05:45","saiu_no_horario":"SIM","data_iso":"2026-06-21"},{"_row":32079,"data":"21/06/2026","maquina":"MAQUINA 01","linha":"420","work_id":"34200201","carro":"3148","motorista":"12580","preparo":"05:32","horario_de_saida_da_garagem":"05:42","saida_real":"05:33","saiu_no_horaro":"SIM","minutos_atrasado_garagem":"","minutos_adiantado_garagem":"","saida_atrasado_adiantado":"NO HORÁRIO","local_inicio":"TMG-T.M.GAV","trajeto_ocioso_correto":"SIM","horario_de_inicio":"05:52","inicio_real":"05:53","inicio_no_horario":"NO HORÁRIO","observacoes":"","minutos_atrasado_no_inicio":"","minutos_adiantado_no_inicio":"","horario_saida_da_garagem":"05:42","saiu_no_horario":"SIM","data_iso":"2026-06-21"},{"_row":32078,"data":"21/06/2026","maquina":"MAQUINA 01","linha":"315","work_id":"33150101","carro":"3139","motorista":"11403","preparo":"05:30","horario_de_saida_da_garagem":"05:40","saida_real":"05:30","saiu_no_horaro":"SIM","minutos_atrasado_garagem":"","minutos_adiantado_garagem":"","saida_atrasado_adiantado":"NO HORÁRIO","local_inicio":"BAIRRO","trajeto_ocioso_correto":"NÃO","horario_de_inicio":"05:50","inicio_real":"05:55","inicio_no_horario":"ATRASADO","observacoes":"","minutos_atrasado_no_inicio":"00:05","minutos_adiantado_no_inicio":"","horario_saida_da_garagem":"05:40","saiu_no_horario":"SIM","data_iso":"2026-06-21"},{"_row":32077,"data":"21/06/2026","maquina":"MAQUINA 01","linha":"405","work_id":"34050201","carro":"3134","motorista":"12490","preparo":"05:26","horario_de_saida_da_garagem":"05:36","saida_real":"05:36","saiu_no_horaro":"SIM","minutos_atrasado_garagem":"","minutos_adiantado_garagem":"","saida_atrasado_adiantado":"NO HORÁRIO","local_inicio":"BAIRRO","trajeto_ocioso_correto":"SIM","horario_de_inicio":"05:46","inicio_real":"05:50","inicio_no_horario":"ATRASADO","observacoes":"","minutos_atrasado_no_inicio":"00:04","minutos_adiantado_no_inicio":"","horario_saida_da_garagem":"05:36","saiu_no_horario":"SIM","data_iso":"2026-06-21"},{"_row":32076,"data":"21/06/2026","maquina":"MAQUINA 01","linha":"112","work_id":"31120301","carro":"3133","motorista":"12578","preparo":"05:25","horario_de_saida_da_garagem":"05:35","saida_real":"05:35","saiu_no_horaro":"SIM","minutos_atrasado_garagem":"","minutos_adiantado_garagem":"","saida_atrasado_adiantado":"NO HORÁRIO","local_inicio":"BAIRRO","trajeto_ocioso_correto":"NÃO","horario_de_inicio":"05:45","inicio_real":"05:42","inicio_no_horario":"ADIANTADO","observacoes":"NÃO INICIO NO LOCAL CORRETO","minutos_atrasado_no_inicio":"","minutos_adiantado_no_inicio":"00:02","horario_saida_da_garagem":"05:35","saiu_no_horario":"SIM","data_iso":"2026-06-21"},{"_row":32075,"data":"21/06/2026","maquina":"MAQUINA 01","linha":"121","work_id":"31210101","carro":"3068","motorista":"12089","preparo":"05:24","horario_de_saida_da_garagem":"05:34","saida_real":"05:26","saiu_no_horaro":"SIM","minutos_atrasado_garagem":"","minutos_adiantado_garagem":"","saida_atrasado_adiantado":"NO HORÁRIO","local_inicio":"BAIRRO","trajeto_ocioso_correto":"SIM","horario_de_inicio":"05:46","inicio_real":"05:37","inicio_no_horario":"ADIANTADO","observacoes":"","minutos_atrasado_no_inicio":"","minutos_adiantado_no_inicio":"00:08","horario_saida_da_garagem":"05:34","saiu_no_horario":"SIM","data_iso":"2026-06-21"},{"_row":32074,"data":"21/06/2026","maquina":"MAQUINA 01","linha":"406","work_id":"34060201","carro":"3132","motorista":"13001","preparo":"05:20","horario_de_saida_da_garagem":"05:30","saida_real":"05:24","saiu_no_horaro":"SIM","minutos_atrasado_garagem":"","minutos_adiantado_garagem":"","saida_atrasado_adiantado":"NO HORÁRIO","local_inicio":"BAIRRO","trajeto_ocioso_correto":"NÃO","horario_de_inicio":"05:40","inicio_real":"05:41","inicio_no_horario":"NO HORÁRIO","observacoes":"","minutos_atrasado_no_inicio":"","minutos_adiantado_no_inicio":"","horario_saida_da_garagem":"05:30","saiu_no_horario":"SIM","data_iso":"2026-06-21"},{"_row":32073,"data":"21/06/2026","maquina":"MAQUINA 01","linha":"109","work_id":"31090101","carro":"3066","motorista":"10753","preparo":"05:17","horario_de_saida_da_garagem":"05:27","saida_real":"05:29","saiu_no_horaro":"SIM","minutos_atrasado_garagem":"","minutos_adiantado_garagem":"","saida_atrasado_adiantado":"NO HORÁRIO","local_inicio":"RODOVIARIA","trajeto_ocioso_correto":"SIM","horario_de_inicio":"05:37","inicio_real":"05:37","inicio_no_horario":"NO HORÁRIO","observacoes":"","minutos_atrasado_no_inicio":"","minutos_adiantado_no_inicio":"","horario_saida_da_garagem":"05:27","saiu_no_horario":"SIM","data_iso":"2026-06-21"},{"_row":32072,"data":"21/06/2026","maquina":"MAQUINA 01","linha":"406","work_id":"34060301","carro":"3131","motorista":"12204","preparo":"05:15","horario_de_saida_da_garagem":"05:25","saida_real":"05:19","saiu_no_horaro":"SIM","minutos_atrasado_garagem":"","minutos_adiantado_garagem":"","saida_atrasado_adiantado":"NO HORÁRIO","local_inicio":"TCI-T.C INF.","trajeto_ocioso_correto":"SIM","horario_de_inicio":"05:35","inicio_real":"05:35","inicio_no_horario":"NO HORÁRIO","observacoes":"","minutos_atrasado_no_inicio":"","minutos_adiantado_no_inicio":"","horario_saida_da_garagem":"05:25","saiu_no_horario":"SIM","data_iso":"2026-06-21"},{"_row":32071,"data":"21/06/2026","maquina":"MAQUINA 01","linha":"420","work_id":"34200101","carro":"3130","motorista":"12751","preparo":"05:10","horario_de_saida_da_garagem":"05:20","saida_real":"05:20","saiu_no_horaro":"SIM","minutos_atrasado_garagem":"","minutos_adiantado_garagem":"","saida_atrasado_adiantado":"NO HORÁRIO","local_inicio":"TVX-V.XAVIER","trajeto_ocioso_correto":"SIM","horario_de_inicio":"05:40","inicio_real":"05:41","inicio_no_horario":"NO HORÁRIO","observacoes":"","minutos_atrasado_no_inicio":"","minutos_adiantado_no_inicio":"","horario_saida_da_garagem":"05:20","saiu_no_horario":"SIM","data_iso":"2026-06-21"},{"_row":32070,"data":"21/06/2026","maquina":"MAQUINA 01","linha":"102","work_id":"31020101","carro":"3180","motorista":"12022","preparo":"05:10","horario_de_saida_da_garagem":"05:20","saida_real":"05:17","saiu_no_horaro":"SIM","minutos_atrasado_garagem":"","minutos_adiantado_garagem":"","saida_atrasado_adiantado":"NO HORÁRIO","local_inicio":"BAIRRO","trajeto_ocioso_correto":"SIM","horario_de_inicio":"05:25","inicio_real":"05:28","inicio_no_horario":"NO HORÁRIO","observacoes":"","minutos_atrasado_no_inicio":"","minutos_adiantado_no_inicio":"","horario_saida_da_garagem":"05:20","saiu_no_horario":"SIM","data_iso":"2026-06-21"},{"_row":32069,"data":"21/06/2026","maquina":"MAQUINA 01","linha":"501","work_id":"35010201","carro":"3163","motorista":"13226","preparo":"05:10","horario_de_saida_da_garagem":"05:20","saida_real":"05:16","saiu_no_horaro":"SIM","minutos_atrasado_garagem":"","minutos_adiantado_garagem":"","saida_atrasado_adiantado":"NO HORÁRIO","local_inicio":"TCI-T.C INF.","trajeto_ocioso_correto":"SIM","horario_de_inicio":"05:30","inicio_real":"05:31","inicio_no_horario":"NO HORÁRIO","observacoes":"","minutos_atrasado_no_inicio":"","minutos_adiantado_no_inicio":"","horario_saida_da_garagem":"05:20","saiu_no_horario":"SIM","data_iso":"2026-06-21"},{"_row":32068,"data":"21/06/2026","maquina":"MAQUINA 01","linha":"311","work_id":"33110201","carro":"3166","motorista":"5040","preparo":"05:10","horario_de_saida_da_garagem":"05:20","saida_real":"05:20","saiu_no_horaro":"SIM","minutos_atrasado_garagem":"","minutos_adiantado_garagem":"","saida_atrasado_adiantado":"NO HORÁRIO","local_inicio":"TCI-T.C INF.","trajeto_ocioso_correto":"SIM","horario_de_inicio":"05:30","inicio_real":"05:31","inicio_no_horario":"NO HORÁRIO","observacoes":"","minutos_atrasado_no_inicio":"","minutos_adiantado_no_inicio":"","horario_saida_da_garagem":"05:20","saiu_no_horario":"SIM","data_iso":"2026-06-21"},{"_row":32067,"data":"21/06/2026","maquina":"MAQUINA 01","linha":"502","work_id":"35020101","carro":"3149","motorista":"13061","preparo":"05:10","horario_de_saida_da_garagem":"05:20","saida_real":"05:16","saiu_no_horaro":"SIM","minutos_atrasado_garagem":"","minutos_adiantado_garagem":"","saida_atrasado_adiantado":"NO HORÁRIO","local_inicio":"TOV-T.O.VERDE","trajeto_ocioso_correto":"SIM","horario_de_inicio":"05:35","inicio_real":"05:34","inicio_no_horario":"NO HORÁRIO","observacoes":"","minutos_atrasado_no_inicio":"","minutos_adiantado_no_inicio":"30/12/1899","horario_saida_da_garagem":"05:20","saiu_no_horario":"SIM","data_iso":"2026-06-21"},{"_row":32066,"data":"21/06/2026","maquina":"MAQUINA 01","linha":"302","work_id":"33020101","carro":"3142","motorista":"12017","preparo":"05:10","horario_de_saida_da_garagem":"05:20","saida_real":"05:14","saiu_no_horaro":"SIM","minutos_atrasado_garagem":"","minutos_adiantado_garagem":"","saida_atrasado_adiantado":"NO HORÁRIO","local_inicio":"BAIRRO","trajeto_ocioso_correto":"SIM","horario_de_inicio":"05:30","inicio_real":"05:29","inicio_no_horario":"NO HORÁRIO","observacoes":"","minutos_atrasado_no_inicio":"","minutos_adiantado_no_inicio":"30/12/1899","horario_saida_da_garagem":"05:20","saiu_no_horario":"SIM","data_iso":"2026-06-21"},{"_row":32065,"data":"21/06/2026","maquina":"MAQUINA 01","linha":"104","work_id":"31040101","carro":"3123","motorista":"12257","preparo":"05:10","horario_de_saida_da_garagem":"05:20","saida_real":"05:13","saiu_no_horaro":"SIM","minutos_atrasado_garagem":"","minutos_adiantado_garagem":"","saida_atrasado_adiantado":"NO HORÁRIO","local_inicio":"BAIRRO","trajeto_ocioso_correto":"SIM","horario_de_inicio":"05:25","inicio_real":"05:25","inicio_no_horario":"NO HORÁRIO","observacoes":"","minutos_atrasado_no_inicio":"","minutos_adiantado_no_inicio":"","horario_saida_da_garagem":"05:20","saiu_no_horario":"SIM","data_iso":"2026-06-21"},{"_row":32064,"data":"21/06/2026","maquina":"MAQUINA 01","linha":"101","work_id":"31010101","carro":"3129","motorista":"7837","preparo":"05:10","horario_de_saida_da_garagem":"05:20","saida_real":"05:19","saiu_no_horaro":"SIM","minutos_atrasado_garagem":"","minutos_adiantado_garagem":"","saida_atrasado_adiantado":"NO HORÁRIO","local_inicio":"BAIRRO","trajeto_ocioso_correto":"SIM","horario_de_inicio":"05:25","inicio_real":"05:29","inicio_no_horario":"ATRASADO","observacoes":"","minutos_atrasado_no_inicio":"00:04","minutos_adiantado_no_inicio":"","horario_saida_da_garagem":"05:20","saiu_no_horario":"SIM","data_iso":"2026-06-21"},{"_row":32063,"data":"21/06/2026","maquina":"MAQUINA 01","linha":"106","work_id":"31060201","carro":"3136","motorista":"12000","preparo":"05:10","horario_de_saida_da_garagem":"05:20","saida_real":"05:22","saiu_no_horaro":"SIM","minutos_atrasado_garagem":"","minutos_adiantado_garagem":"","saida_atrasado_adiantado":"NO HORÁRIO","local_inicio":"TCI-T.C INF.","trajeto_ocioso_correto":"SIM","horario_de_inicio":"05:30","inicio_real":"05:33","inicio_no_horario":"NO HORÁRIO","observacoes":"","minutos_atrasado_no_inicio":"","minutos_adiantado_no_inicio":"","horario_saida_da_garagem":"05:20","saiu_no_horario":"SIM","data_iso":"2026-06-21"},{"_row":32062,"data":"21/06/2026","maquina":"MAQUINA 01","linha":"307","work_id":"33070101","carro":"3010","motorista":"12205","preparo":"05:10","horario_de_saida_da_garagem":"05:20","saida_real":"05:20","saiu_no_horaro":"SIM","minutos_atrasado_garagem":"","minutos_adiantado_garagem":"","saida_atrasado_adiantado":"NO HORÁRIO","local_inicio":"TCI-T.C INF.","trajeto_ocioso_correto":"SIM","horario_de_inicio":"05:30","inicio_real":"05:30","inicio_no_horario":"NO HORÁRIO","observacoes":"","minutos_atrasado_no_inicio":"","minutos_adiantado_no_inicio":"","horario_saida_da_garagem":"05:20","saiu_no_horario":"SIM","data_iso":"2026-06-21"},{"_row":32061,"data":"21/06/2026","maquina":"MAQUINA 01","linha":"110","work_id":"31100301","carro":"3137","motorista":"10586","preparo":"05:10","horario_de_saida_da_garagem":"05:20","saida_real":"05:21","saiu_no_horaro":"SIM","minutos_atrasado_garagem":"","minutos_adiantado_garagem":"","saida_atrasado_adiantado":"NO HORÁRIO","local_inicio":"TCI-T.C INF.","trajeto_ocioso_correto":"SIM","horario_de_inicio":"05:30","inicio_real":"05:30","inicio_no_horario":"NO HORÁRIO","observacoes":"","minutos_atrasado_no_inicio":"","minutos_adiantado_no_inicio":"","horario_saida_da_garagem":"05:20","saiu_no_horario":"SIM","data_iso":"2026-06-21"},{"_row":32060,"data":"21/06/2026","maquina":"MAQUINA 01","linha":"904","work_id":"39040201","carro":"1162","motorista":"12939","preparo":"05:06","horario_de_saida_da_garagem":"05:16","saida_real":"05:16","saiu_no_horaro":"SIM","minutos_atrasado_garagem":"","minutos_adiantado_garagem":"","saida_atrasado_adiantado":"NO HORÁRIO","local_inicio":"TRO-T.R.OESTE","trajeto_ocioso_correto":"SIM","horario_de_inicio":"05:31","inicio_real":"05:31","inicio_no_horario":"NO HORÁRIO","observacoes":"","minutos_atrasado_no_inicio":"","minutos_adiantado_no_inicio":"","horario_saida_da_garagem":"05:16","saiu_no_horario":"SIM","data_iso":"2026-06-21"},{"_row":32059,"data":"21/06/2026","maquina":"MAQUINA 01","linha":"303","work_id":"33030201","carro":"3153","motorista":"12493","preparo":"05:05","horario_de_saida_da_garagem":"05:15","saida_real":"05:15","saiu_no_horaro":"SIM","minutos_atrasado_garagem":"","minutos_adiantado_garagem":"","saida_atrasado_adiantado":"NO HORÁRIO","local_inicio":"BAIRRO","trajeto_ocioso_correto":"SIM","horario_de_inicio":"05:25","inicio_real":"05:28","inicio_no_horario":"NO HORÁRIO","observacoes":"","minutos_atrasado_no_inicio":"","minutos_adiantado_no_inicio":"","horario_saida_da_garagem":"05:15","saiu_no_horario":"SIM","data_iso":"2026-06-21"},{"_row":32058,"data":"21/06/2026","maquina":"MAQUINA 01","linha":"407","work_id":"34070101","carro":"3122","motorista":"12045","preparo":"05:05","horario_de_saida_da_garagem":"05:15","saida_real":"05:12","saiu_no_horaro":"SIM","minutos_atrasado_garagem":"","minutos_adiantado_garagem":"","saida_atrasado_adiantado":"NO HORÁRIO","local_inicio":"BAIRRO","trajeto_ocioso_correto":"SIM","horario_de_inicio":"05:20","inicio_real":"05:20","inicio_no_horario":"NO HORÁRIO","observacoes":"","minutos_atrasado_no_inicio":"","minutos_adiantado_no_inicio":"","horario_saida_da_garagem":"05:15","saiu_no_horario":"SIM","data_iso":"2026-06-21"},{"_row":32057,"data":"21/06/2026","maquina":"MAQUINA 01","linha":"303","work_id":"33030101","carro":"3138","motorista":"12180","preparo":"05:05","horario_de_saida_da_garagem":"05:15","saida_real":"05:15","saiu_no_horaro":"SIM","minutos_atrasado_garagem":"","minutos_adiantado_garagem":"","saida_atrasado_adiantado":"NO HORÁRIO","local_inicio":"BAIRRO","trajeto_ocioso_correto":"SIM","horario_de_inicio":"05:25","inicio_real":"05:25","inicio_no_horario":"NO HORÁRIO","observacoes":"","minutos_atrasado_no_inicio":"","minutos_adiantado_no_inicio":"","horario_saida_da_garagem":"05:15","saiu_no_horario":"SIM","data_iso":"2026-06-21"},{"_row":32056,"data":"21/06/2026","maquina":"MAQUINA 01","linha":"106","work_id":"31060101","carro":"3125","motorista":"10576","preparo":"05:05","horario_de_saida_da_garagem":"05:15","saida_real":"05:09","saiu_no_horaro":"SIM","minutos_atrasado_garagem":"","minutos_adiantado_garagem":"","saida_atrasado_adiantado":"NO HORÁRIO","local_inicio":"BAIRRO","trajeto_ocioso_correto":"SIM","horario_de_inicio":"05:25","inicio_real":"05:25","inicio_no_horario":"NO HORÁRIO","observacoes":"","minutos_atrasado_no_inicio":"","minutos_adiantado_no_inicio":"","horario_saida_da_garagem":"05:15","saiu_no_horario":"SIM","data_iso":"2026-06-21"},{"_row":32055,"data":"21/06/2026","maquina":"MAQUINA 01","linha":"301","work_id":"33010101","carro":"3124","motorista":"13132","preparo":"05:05","horario_de_saida_da_garagem":"05:15","saida_real":"05:15","saiu_no_horaro":"SIM","minutos_atrasado_garagem":"","minutos_adiantado_garagem":"","saida_atrasado_adiantado":"NO HORÁRIO","local_inicio":"BAIRRO","trajeto_ocioso_correto":"SIM","horario_de_inicio":"05:25","inicio_real":"05:25","inicio_no_horario":"NO HORÁRIO","observacoes":"","minutos_atrasado_no_inicio":"","minutos_adiantado_no_inicio":"","horario_saida_da_garagem":"05:15","saiu_no_horario":"SIM","data_iso":"2026-06-21"},{"_row":32054,"data":"21/06/2026","maquina":"MAQUINA 01","linha":"112","work_id":"31120101","carro":"3178","motorista":"13094","preparo":"05:05","horario_de_saida_da_garagem":"05:15","saida_real":"05:06","saiu_no_horaro":"SIM","minutos_atrasado_garagem":"","minutos_adiantado_garagem":"","saida_atrasado_adiantado":"NO HORÁRIO","local_inicio":"BAIRRO","trajeto_ocioso_correto":"SIM","horario_de_inicio":"05:20","inicio_real":"05:20","inicio_no_horario":"NO HORÁRIO","observacoes":"","minutos_atrasado_no_inicio":"","minutos_adiantado_no_inicio":"","horario_saida_da_garagem":"05:15","saiu_no_horario":"SIM","data_iso":"2026-06-21"},{"_row":32053,"data":"21/06/2026","maquina":"MAQUINA 01","linha":"904","work_id":"39040301","carro":"1161","motorista":"12986","preparo":"05:05","horario_de_saida_da_garagem":"05:15","saida_real":"05:15","saiu_no_horaro":"SIM","minutos_atrasado_garagem":"","minutos_adiantado_garagem":"","saida_atrasado_adiantado":"NO HORÁRIO","local_inicio":"TAC-T.ACAP","trajeto_ocioso_correto":"SIM","horario_de_inicio":"05:35","inicio_real":"05:35","inicio_no_horario":"NO HORÁRIO","observacoes":"","minutos_atrasado_no_inicio":"","minutos_adiantado_no_inicio":"","horario_saida_da_garagem":"05:15","saiu_no_horario":"SIM","data_iso":"2026-06-21"},{"_row":32052,"data":"21/06/2026","maquina":"MAQUINA 01","linha":"311","work_id":"33110101","carro":"3160","motorista":"12477","preparo":"05:03","horario_de_saida_da_garagem":"05:13","saida_real":"05:14","saiu_no_horaro":"SIM","minutos_atrasado_garagem":"","minutos_adiantado_garagem":"","saida_atrasado_adiantado":"NO HORÁRIO","local_inicio":"BAIRRO","trajeto_ocioso_correto":"SIM","horario_de_inicio":"05:20","inicio_real":"05:23","inicio_no_horario":"NO HORÁRIO","observacoes":"","minutos_atrasado_no_inicio":"","minutos_adiantado_no_inicio":"","horario_saida_da_garagem":"05:13","saiu_no_horario":"SIM","data_iso":"2026-06-21"},{"_row":32051,"data":"21/06/2026","maquina":"MAQUINA 01","linha":"308","work_id":"33080101","carro":"3170","motorista":"10540","preparo":"05:00","horario_de_saida_da_garagem":"05:10","saida_real":"05:07","saiu_no_horaro":"SIM","minutos_atrasado_garagem":"","minutos_adiantado_garagem":"","saida_atrasado_adiantado":"NO HORÁRIO","local_inicio":"BAIRRO","trajeto_ocioso_correto":"SIM","horario_de_inicio":"05:20","inicio_real":"05:20","inicio_no_horario":"NO HORÁRIO","observacoes":"","minutos_atrasado_no_inicio":"","minutos_adiantado_no_inicio":"","horario_saida_da_garagem":"05:10","saiu_no_horario":"SIM","data_iso":"2026-06-21"},{"_row":32050,"data":"21/06/2026","maquina":"MAQUINA 01","linha":"107","work_id":"31070101","carro":"3147","motorista":"7822","preparo":"05:00","horario_de_saida_da_garagem":"05:10","saida_real":"05:06","saiu_no_horaro":"SIM","minutos_atrasado_garagem":"","minutos_adiantado_garagem":"","saida_atrasado_adiantado":"NO HORÁRIO","local_inicio":"BAIRRO","trajeto_ocioso_correto":"SIM","horario_de_inicio":"05:25","inicio_real":"05:25","inicio_no_horario":"NO HORÁRIO","observacoes":"","minutos_atrasado_no_inicio":"","minutos_adiantado_no_inicio":"","horario_saida_da_garagem":"05:10","saiu_no_horario":"SIM","data_iso":"2026-06-21"},{"_row":32049,"data":"21/06/2026","maquina":"MAQUINA 01","linha":"501","work_id":"35010101","carro":"3144","motorista":"12734","preparo":"05:00","horario_de_saida_da_garagem":"05:10","saida_real":"05:03","saiu_no_horaro":"SIM","minutos_atrasado_garagem":"","minutos_adiantado_garagem":"","saida_atrasado_adiantado":"NO HORÁRIO","local_inicio":"BAIRRO","trajeto_ocioso_correto":"SIM","horario_de_inicio":"05:25","inicio_real":"05:25","inicio_no_horario":"NO HORÁRIO","observacoes":"","minutos_atrasado_no_inicio":"","minutos_adiantado_no_inicio":"","horario_saida_da_garagem":"05:10","saiu_no_horario":"SIM","data_iso":"2026-06-21"},{"_row":32048,"data":"21/06/2026","maquina":"MAQUINA 01","linha":"314","work_id":"33140201","carro":"3171","motorista":"13332","preparo":"05:00","horario_de_saida_da_garagem":"05:10","saida_real":"05:00","saiu_no_horaro":"SIM","minutos_atrasado_garagem":"","minutos_adiantado_garagem":"","saida_atrasado_adiantado":"NO HORÁRIO","local_inicio":"BAIRRO","trajeto_ocioso_correto":"SIM","horario_de_inicio":"05:25","inicio_real":"05:25","inicio_no_horario":"NO HORÁRIO","observacoes":"","minutos_atrasado_no_inicio":"","minutos_adiantado_no_inicio":"","horario_saida_da_garagem":"05:10","saiu_no_horario":"SIM","data_iso":"2026-06-21"},{"_row":32047,"data":"21/06/2026","maquina":"MAQUINA 01","linha":"112","work_id":"31120201","carro":"3157","motorista":"9845","preparo":"05:00","horario_de_saida_da_garagem":"05:10","saida_real":"05:06","saiu_no_horaro":"SIM","minutos_atrasado_garagem":"","minutos_adiantado_garagem":"","saida_atrasado_adiantado":"NO HORÁRIO","local_inicio":"BAIRRO","trajeto_ocioso_correto":"SIM","horario_de_inicio":"05:20","inicio_real":"05:20","inicio_no_horario":"NO HORÁRIO","observacoes":"","minutos_atrasado_no_inicio":"","minutos_adiantado_no_inicio":"","horario_saida_da_garagem":"05:10","saiu_no_horario":"SIM","data_iso":"2026-06-21"},{"_row":32046,"data":"21/06/2026","maquina":"MAQUINA 01","linha":"110","work_id":"31100101","carro":"3155","motorista":"12084","preparo":"05:00","horario_de_saida_da_garagem":"05:10","saida_real":"05:03","saiu_no_horaro":"SIM","minutos_atrasado_garagem":"","minutos_adiantado_garagem":"","saida_atrasado_adiantado":"NO HORÁRIO","local_inicio":"BAIRRO","trajeto_ocioso_correto":"SIM","horario_de_inicio":"05:15","inicio_real":"05:15","inicio_no_horario":"NO HORÁRIO","observacoes":"","minutos_atrasado_no_inicio":"","minutos_adiantado_no_inicio":"","horario_saida_da_garagem":"05:10","saiu_no_horario":"SIM","data_iso":"2026-06-21"},{"_row":32045,"data":"21/06/2026","maquina":"MAQUINA 01","linha":"425","work_id":"34250101","carro":"3175","motorista":"7661","preparo":"05:00","horario_de_saida_da_garagem":"05:10","saida_real":"05:05","saiu_no_horaro":"SIM","minutos_atrasado_garagem":"","minutos_adiantado_garagem":"","saida_atrasado_adiantado":"NO HORÁRIO","local_inicio":"BAIRRO","trajeto_ocioso_correto":"SIM","horario_de_inicio":"05:20","inicio_real":"05:20","inicio_no_horario":"NO HORÁRIO","observacoes":"","minutos_atrasado_no_inicio":"","minutos_adiantado_no_inicio":"","horario_saida_da_garagem":"05:10","saiu_no_horario":"SIM","data_iso":"2026-06-21"},{"_row":32044,"data":"21/06/2026","maquina":"MAQUINA 01","linha":"313","work_id":"33130101","carro":"3156","motorista":"12075","preparo":"04:58","horario_de_saida_da_garagem":"05:08","saida_real":"05:06","saiu_no_horaro":"SIM","minutos_atrasado_garagem":"","minutos_adiantado_garagem":"","saida_atrasado_adiantado":"NO HORÁRIO","local_inicio":"BAIRRO","trajeto_ocioso_correto":"SIM","horario_de_inicio":"05:18","inicio_real":"05:18","inicio_no_horario":"NO HORÁRIO","observacoes":"","minutos_atrasado_no_inicio":"","minutos_adiantado_no_inicio":"","horario_saida_da_garagem":"05:08","saiu_no_horario":"SIM","data_iso":"2026-06-21"},{"_row":32043,"data":"21/06/2026","maquina":"MAQUINA 01","linha":"415","work_id":"34150101","carro":"3152","motorista":"12078","preparo":"04:55","horario_de_saida_da_garagem":"05:05","saida_real":"05:00","saiu_no_horaro":"SIM","minutos_atrasado_garagem":"","minutos_adiantado_garagem":"","saida_atrasado_adiantado":"NO HORÁRIO","local_inicio":"BAIRRO","trajeto_ocioso_correto":"SIM","horario_de_inicio":"05:15","inicio_real":"05:15","inicio_no_horario":"NO HORÁRIO","observacoes":"","minutos_atrasado_no_inicio":"","minutos_adiantado_no_inicio":"","horario_saida_da_garagem":"05:05","saiu_no_horario":"SIM","data_iso":"2026-06-21"},{"_row":32042,"data":"21/06/2026","maquina":"MAQUINA 01","linha":"404","work_id":"34040101","carro":"3164","motorista":"8525","preparo":"04:55","horario_de_saida_da_garagem":"05:05","saida_real":"05:07","saiu_no_horaro":"SIM","minutos_atrasado_garagem":"","minutos_adiantado_garagem":"","saida_atrasado_adiantado":"NO HORÁRIO","local_inicio":"BAIRRO","trajeto_ocioso_correto":"SIM","horario_de_inicio":"05:15","inicio_real":"05:18","inicio_no_horario":"NO HORÁRIO","observacoes":"","minutos_atrasado_no_inicio":"","minutos_adiantado_no_inicio":"","horario_saida_da_garagem":"05:05","saiu_no_horario":"SIM","data_iso":"2026-06-21"},{"_row":32041,"data":"21/06/2026","maquina":"MAQUINA 01","linha":"108","work_id":"31080101","carro":"3162","motorista":"8651","preparo":"04:55","horario_de_saida_da_garagem":"05:05","saida_real":"05:04","saiu_no_horaro":"SIM","minutos_atrasado_garagem":"","minutos_adiantado_garagem":"","saida_atrasado_adiantado":"NO HORÁRIO","local_inicio":"BAIRRO","trajeto_ocioso_correto":"SIM","horario_de_inicio":"05:10","inicio_real":"05:13","inicio_no_horario":"NO HORÁRIO","observacoes":"","minutos_atrasado_no_inicio":"","minutos_adiantado_no_inicio":"","horario_saida_da_garagem":"05:05","saiu_no_horario":"SIM","data_iso":"2026-06-21"},{"_row":32040,"data":"21/06/2026","maquina":"MAQUINA 01","linha":"413","work_id":"34130101","carro":"3174","motorista":"12011","preparo":"04:55","horario_de_saida_da_garagem":"05:05","saida_real":"05:00","saiu_no_horaro":"SIM","minutos_atrasado_garagem":"","minutos_adiantado_garagem":"","saida_atrasado_adiantado":"NO HORÁRIO","local_inicio":"BAIRRO","trajeto_ocioso_correto":"SIM","horario_de_inicio":"05:15","inicio_real":"05:15","inicio_no_horario":"NO HORÁRIO","observacoes":"","minutos_atrasado_no_inicio":"","minutos_adiantado_no_inicio":"","horario_saida_da_garagem":"05:05","saiu_no_horario":"SIM","data_iso":"2026-06-21"},{"_row":32039,"data":"21/06/2026","maquina":"MAQUINA 01","linha":"307","work_id":"33070201","carro":"3009","motorista":"10084","preparo":"04:55","horario_de_saida_da_garagem":"05:05","saida_real":"05:07","saiu_no_horaro":"SIM","minutos_atrasado_garagem":"","minutos_adiantado_garagem":"","saida_atrasado_adiantado":"NO HORÁRIO","local_inicio":"BAIRRO","trajeto_ocioso_correto":"SIM","horario_de_inicio":"05:20","inicio_real":"05:25","inicio_no_horario":"ATRASADO","observacoes":"","minutos_atrasado_no_inicio":"00:05","minutos_adiantado_no_inicio":"","horario_saida_da_garagem":"05:05","saiu_no_horario":"SIM","data_iso":"2026-06-21"},{"_row":32038,"data":"21/06/2026","maquina":"MAQUINA 01","linha":"406","work_id":"34060101","carro":"3159","motorista":"12658","preparo":"04:55","horario_de_saida_da_garagem":"05:05","saida_real":"05:07","saiu_no_horaro":"SIM","minutos_atrasado_garagem":"","minutos_adiantado_garagem":"","saida_atrasado_adiantado":"NO HORÁRIO","local_inicio":"BAIRRO","trajeto_ocioso_correto":"SIM","horario_de_inicio":"05:15","inicio_real":"05:15","inicio_no_horario":"NO HORÁRIO","observacoes":"","minutos_atrasado_no_inicio":"","minutos_adiantado_no_inicio":"","horario_saida_da_garagem":"05:05","saiu_no_horario":"SIM","data_iso":"2026-06-21"},{"_row":32037,"data":"21/06/2026","maquina":"MAQUINA 01","linha":"414","work_id":"34140101","carro":"3165","motorista":"10582","preparo":"04:50","horario_de_saida_da_garagem":"05:00","saida_real":"05:02","saiu_no_horaro":"SIM","minutos_atrasado_garagem":"","minutos_adiantado_garagem":"","saida_atrasado_adiantado":"NO HORÁRIO","local_inicio":"BAIRRO","trajeto_ocioso_correto":"SIM","horario_de_inicio":"05:10","inicio_real":"05:10","inicio_no_horario":"NO HORÁRIO","observacoes":"","minutos_atrasado_no_inicio":"","minutos_adiantado_no_inicio":"","horario_saida_da_garagem":"05:00","saiu_no_horario":"SIM","data_iso":"2026-06-21"},{"_row":32036,"data":"21/06/2026","maquina":"MAQUINA 01","linha":"412","work_id":"34120101","carro":"3135","motorista":"13125","preparo":"04:50","horario_de_saida_da_garagem":"05:00","saida_real":"04:58","saiu_no_horaro":"SIM","minutos_atrasado_garagem":"","minutos_adiantado_garagem":"","saida_atrasado_adiantado":"NO HORÁRIO","local_inicio":"BAIRRO","trajeto_ocioso_correto":"SIM","horario_de_inicio":"05:10","inicio_real":"05:10","inicio_no_horario":"NO HORÁRIO","observacoes":"","minutos_atrasado_no_inicio":"","minutos_adiantado_no_inicio":"","horario_saida_da_garagem":"05:00","saiu_no_horario":"SIM","data_iso":"2026-06-21"},{"_row":32035,"data":"21/06/2026","maquina":"MAQUINA 01","linha":"309","work_id":"33090101","carro":"3083","motorista":"12875","preparo":"04:50","horario_de_saida_da_garagem":"05:00","saida_real":"04:56","saiu_no_horaro":"SIM","minutos_atrasado_garagem":"","minutos_adiantado_garagem":"","saida_atrasado_adiantado":"NO HORÁRIO","local_inicio":"BAIRRO","trajeto_ocioso_correto":"SIM","horario_de_inicio":"05:10","inicio_real":"05:10","inicio_no_horario":"NO HORÁRIO","observacoes":"","minutos_atrasado_no_inicio":"","minutos_adiantado_no_inicio":"","horario_saida_da_garagem":"05:00","saiu_no_horario":"SIM","data_iso":"2026-06-21"},{"_row":32034,"data":"21/06/2026","maquina":"MAQUINA 01","linha":"405","work_id":"34050101","carro":"3151","motorista":"9166","preparo":"04:50","horario_de_saida_da_garagem":"05:00","saida_real":"04:56","saiu_no_horaro":"SIM","minutos_atrasado_garagem":"","minutos_adiantado_garagem":"","saida_atrasado_adiantado":"NO HORÁRIO","local_inicio":"BAIRRO","trajeto_ocioso_correto":"SIM","horario_de_inicio":"05:10","inicio_real":"05:10","inicio_no_horario":"NO HORÁRIO","observacoes":"","minutos_atrasado_no_inicio":"","minutos_adiantado_no_inicio":"","horario_saida_da_garagem":"05:00","saiu_no_horario":"SIM","data_iso":"2026-06-21"},{"_row":32033,"data":"21/06/2026","maquina":"MAQUINA 01","linha":"421","work_id":"34210101","carro":"4603","motorista":"12846","preparo":"04:45","horario_de_saida_da_garagem":"04:55","saida_real":"04:53","saiu_no_horaro":"SIM","minutos_atrasado_garagem":"","minutos_adiantado_garagem":"","saida_atrasado_adiantado":"NO HORÁRIO","local_inicio":"TOV-T.O.VERDE","trajeto_ocioso_correto":"SIM","horario_de_inicio":"05:10","inicio_real":"05:10","inicio_no_horario":"NO HORÁRIO","observacoes":"","minutos_atrasado_no_inicio":"","minutos_adiantado_no_inicio":"","horario_saida_da_garagem":"04:55","saiu_no_horario":"SIM","data_iso":"2026-06-21"},{"_row":32032,"data":"21/06/2026","maquina":"MAQUINA 01","linha":"447","work_id":"34470201","carro":"4601","motorista":"12629","preparo":"04:45","horario_de_saida_da_garagem":"04:55","saida_real":"04:50","saiu_no_horaro":"SIM","minutos_atrasado_garagem":"","minutos_adiantado_garagem":"","saida_atrasado_adiantado":"NO HORÁRIO","local_inicio":"BAIRRO","trajeto_ocioso_correto":"SIM","horario_de_inicio":"05:10","inicio_real":"05:10","inicio_no_horario":"NO HORÁRIO","observacoes":"","minutos_atrasado_no_inicio":"","minutos_adiantado_no_inicio":"","horario_saida_da_garagem":"04:55","saiu_no_horario":"SIM","data_iso":"2026-06-21"},{"_row":32031,"data":"21/06/2026","maquina":"MAQUINA 01","linha":"419","work_id":"34190101","carro":"3150","motorista":"11457","preparo":"04:45","horario_de_saida_da_garagem":"04:55","saida_real":"05:00","saiu_no_horaro":"NÃO","minutos_atrasado_garagem":"00:05","minutos_adiantado_garagem":"","saida_atrasado_adiantado":"ATRASADO","local_inicio":"BAIRRO","trajeto_ocioso_correto":"SIM","horario_de_inicio":"05:05","inicio_real":"05:05","inicio_no_horario":"NO HORÁRIO","observacoes":"","minutos_atrasado_no_inicio":"","minutos_adiantado_no_inicio":"","horario_saida_da_garagem":"04:55","saiu_no_horario":"NÃO","data_iso":"2026-06-21"},{"_row":32030,"data":"21/06/2026","maquina":"MAQUINA 01","linha":"430","work_id":"34300101","carro":"3145","motorista":"11998","preparo":"04:45","horario_de_saida_da_garagem":"04:55","saida_real":"05:00","saiu_no_horaro":"NÃO","minutos_atrasado_garagem":"00:05","minutos_adiantado_garagem":"","saida_atrasado_adiantado":"ATRASADO","local_inicio":"BAIRRO","trajeto_ocioso_correto":"SIM","horario_de_inicio":"05:10","inicio_real":"05:11","inicio_no_horario":"NO HORÁRIO","observacoes":"","minutos_atrasado_no_inicio":"","minutos_adiantado_no_inicio":"","horario_saida_da_garagem":"04:55","saiu_no_horario":"NÃO","data_iso":"2026-06-21"},{"_row":32029,"data":"21/06/2026","maquina":"MAQUINA 01","linha":"401","work_id":"34010101","carro":"3126","motorista":"11731","preparo":"04:45","horario_de_saida_da_garagem":"04:55","saida_real":"04:54","saiu_no_horaro":"SIM","minutos_atrasado_garagem":"","minutos_adiantado_garagem":"","saida_atrasado_adiantado":"NO HORÁRIO","local_inicio":"BAIRRO","trajeto_ocioso_correto":"SIM","horario_de_inicio":"05:05","inicio_real":"05:05","inicio_no_horario":"NO HORÁRIO","observacoes":"","minutos_atrasado_no_inicio":"","minutos_adiantado_no_inicio":"","horario_saida_da_garagem":"04:55","saiu_no_horario":"SIM","data_iso":"2026-06-21"},{"_row":32028,"data":"21/06/2026","maquina":"MAQUINA 01","linha":"400","work_id":"34000101","carro":"3173","motorista":"12121","preparo":"04:45","horario_de_saida_da_garagem":"04:55","saida_real":"04:54","saiu_no_horaro":"SIM","minutos_atrasado_garagem":"","minutos_adiantado_garagem":"","saida_atrasado_adiantado":"NO HORÁRIO","local_inicio":"BAIRRO","trajeto_ocioso_correto":"SIM","horario_de_inicio":"05:05","inicio_real":"05:05","inicio_no_horario":"NO HORÁRIO","observacoes":"","minutos_atrasado_no_inicio":"","minutos_adiantado_no_inicio":"","horario_saida_da_garagem":"04:55","saiu_no_horario":"SIM","data_iso":"2026-06-21"},{"_row":32027,"data":"21/06/2026","maquina":"MAQUINA 01","linha":"428","work_id":"34280101","carro":"3158","motorista":"8295","preparo":"04:45","horario_de_saida_da_garagem":"04:55","saida_real":"04:51","saiu_no_horaro":"SIM","minutos_atrasado_garagem":"","minutos_adiantado_garagem":"","saida_atrasado_adiantado":"NO HORÁRIO","local_inicio":"BAIRRO","trajeto_ocioso_correto":"SIM","horario_de_inicio":"05:05","inicio_real":"05:05","inicio_no_horario":"NO HORÁRIO","observacoes":"","minutos_atrasado_no_inicio":"","minutos_adiantado_no_inicio":"","horario_saida_da_garagem":"04:55","saiu_no_horario":"SIM","data_iso":"2026-06-21"},{"_row":32026,"data":"21/06/2026","maquina":"MAQUINA 01","linha":"423","work_id":"34230101","carro":"3176","motorista":"12731","preparo":"04:45","horario_de_saida_da_garagem":"04:55","saida_real":"04:52","saiu_no_horaro":"SIM","minutos_atrasado_garagem":"","minutos_adiantado_garagem":"","saida_atrasado_adiantado":"NO HORÁRIO","local_inicio":"BAIRRO","trajeto_ocioso_correto":"SIM","horario_de_inicio":"05:05","inicio_real":"05:05","inicio_no_horario":"NO HORÁRIO","observacoes":"","minutos_atrasado_no_inicio":"","minutos_adiantado_no_inicio":"","horario_saida_da_garagem":"04:55","saiu_no_horario":"SIM","data_iso":"2026-06-21"},{"_row":32025,"data":"21/06/2026","maquina":"MAQUINA 01","linha":"904","work_id":"39040101","carro":"1160","motorista":"12745","preparo":"04:40","horario_de_saida_da_garagem":"04:50","saida_real":"04:46","saiu_no_horaro":"SIM","minutos_atrasado_garagem":"","minutos_adiantado_garagem":"","saida_atrasado_adiantado":"NO HORÁRIO","local_inicio":"TVX-V.XAVIER","trajeto_ocioso_correto":"SIM","horario_de_inicio":"05:10","inicio_real":"05:10","inicio_no_horario":"NO HORÁRIO","observacoes":"","minutos_atrasado_no_inicio":"","minutos_adiantado_no_inicio":"","horario_saida_da_garagem":"04:50","saiu_no_horario":"SIM","data_iso":"2026-06-21"},{"_row":32024,"data":"21/06/2026","maquina":"MAQUINA 01","linha":"314","work_id":"33140101","carro":"3141","motorista":"10864","preparo":"04:25","horario_de_saida_da_garagem":"04:35","saida_real":"04:30","saiu_no_horaro":"SIM","minutos_atrasado_garagem":"","minutos_adiantado_garagem":"","saida_atrasado_adiantado":"NO HORÁRIO","local_inicio":"BAIRRO","trajeto_ocioso_correto":"SIM","horario_de_inicio":"04:50","inicio_real":"04:50","inicio_no_horario":"NO HORÁRIO","observacoes":"","minutos_atrasado_no_inicio":"","minutos_adiantado_no_inicio":"","horario_saida_da_garagem":"04:35","saiu_no_horario":"SIM","data_iso":"2026-06-21"},{"_row":32023,"data":"21/06/2026","maquina":"MAQUINA 01","linha":"103","work_id":"31030101","carro":"3167","motorista":"11368","preparo":"04:10","horario_de_saida_da_garagem":"04:20","saida_real":"04:12","saiu_no_horaro":"SIM","minutos_atrasado_garagem":"","minutos_adiantado_garagem":"","saida_atrasado_adiantado":"NO HORÁRIO","local_inicio":"TCI-T.C INF.","trajeto_ocioso_correto":"SIM","horario_de_inicio":"04:30","inicio_real":"04:30","inicio_no_horario":"NO HORÁRIO","observacoes":"","minutos_atrasado_no_inicio":"","minutos_adiantado_no_inicio":"","horario_saida_da_garagem":"04:20","saiu_no_horario":"SIM","data_iso":"2026-06-21"},{"_row":32022,"data":"21/06/2026","maquina":"MAQUINA 01","linha":"97","work_id":"30970201","carro":"3084","motorista":"11801","preparo":"04:10","horario_de_saida_da_garagem":"04:20","saida_real":"04:11","saiu_no_horaro":"SIM","minutos_atrasado_garagem":"","minutos_adiantado_garagem":"","saida_atrasado_adiantado":"NO HORÁRIO","local_inicio":"TCI-T.C INF.","trajeto_ocioso_correto":"SIM","horario_de_inicio":"04:30","inicio_real":"04:30","inicio_no_horario":"NO HORÁRIO","observacoes":"","minutos_atrasado_no_inicio":"","minutos_adiantado_no_inicio":"","horario_saida_da_garagem":"04:20","saiu_no_horario":"SIM","data_iso":"2026-06-21"},{"_row":32021,"data":"21/06/2026","maquina":"MAQUINA 01","linha":"97","work_id":"30970101","carro":"4611","motorista":"8988","preparo":"00:10","horario_de_saida_da_garagem":"00:20","saida_real":"00:20","saiu_no_horaro":"SIM","minutos_atrasado_garagem":"","minutos_adiantado_garagem":"","saida_atrasado_adiantado":"NO HORÁRIO","local_inicio":"TCI-T.C INF.","trajeto_ocioso_correto":"SIM","horario_de_inicio":"00:30","inicio_real":"00:30","inicio_no_horario":"NO HORÁRIO","observacoes":"","minutos_atrasado_no_inicio":"","minutos_adiantado_no_inicio":"","horario_saida_da_garagem":"00:20","saiu_no_horario":"SIM","data_iso":"2026-06-21"},{"_row":32020,"data":"21/06/2026","maquina":"MAQUINA 01","linha":"96","work_id":"30960101","carro":"4553","motorista":"11755","preparo":"00:10","horario_de_saida_da_garagem":"00:20","saida_real":"00:11","saiu_no_horaro":"SIM","minutos_atrasado_garagem":"","minutos_adiantado_garagem":"","saida_atrasado_adiantado":"NO HORÁRIO","local_inicio":"TCI-T.C INF.","trajeto_ocioso_correto":"SIM","horario_de_inicio":"00:30","inicio_real":"00:30","inicio_no_horario":"NO HORÁRIO","observacoes":"","minutos_atrasado_no_inicio":"","minutos_adiantado_no_inicio":"","horario_saida_da_garagem":"00:20","saiu_no_horario":"SIM","data_iso":"2026-06-21"},{"_row":32019,"data":"21/06/2026","maquina":"MAQUINA 01","linha":"92","work_id":"30920101","carro":"4610","motorista":"12262","preparo":"00:10","horario_de_saida_da_garagem":"00:20","saida_real":"00:15","saiu_no_horaro":"SIM","minutos_atrasado_garagem":"","minutos_adiantado_garagem":"","saida_atrasado_adiantado":"NO HORÁRIO","local_inicio":"TCI-T.C INF.","trajeto_ocioso_correto":"SIM","horario_de_inicio":"00:30","inicio_real":"00:30","inicio_no_horario":"NO HORÁRIO","observacoes":"","minutos_atrasado_no_inicio":"","minutos_adiantado_no_inicio":"","horario_saida_da_garagem":"00:20","saiu_no_horario":"SIM","data_iso":"2026-06-21"},{"_row":32018,"data":"21/06/2026","maquina":"MAQUINA 01","linha":"93","work_id":"30930101","carro":"4555","motorista":"8931","preparo":"00:10","horario_de_saida_da_garagem":"00:20","saida_real":"00:17","saiu_no_horaro":"SIM","minutos_atrasado_garagem":"","minutos_adiantado_garagem":"","saida_atrasado_adiantado":"NO HORÁRIO","local_inicio":"TCI-T.C INF.","trajeto_ocioso_correto":"SIM","horario_de_inicio":"00:30","inicio_real":"00:30","inicio_no_horario":"NO HORÁRIO","observacoes":"","minutos_atrasado_no_inicio":"","minutos_adiantado_no_inicio":"","horario_saida_da_garagem":"00:20","saiu_no_horario":"SIM","data_iso":"2026-06-21"},{"_row":32017,"data":"21/06/2026","maquina":"MAQUINA 01","linha":"91","work_id":"30910101","carro":"4504","motorista":"11860","preparo":"00:10","horario_de_saida_da_garagem":"00:20","saida_real":"00:18","saiu_no_horaro":"SIM","minutos_atrasado_garagem":"","minutos_adiantado_garagem":"teste","saida_atrasado_adiantado":"ADIANTADO","local_inicio":"TCI-T.C INF.","trajeto_ocioso_correto":"SIM","horario_de_inicio":"00:30","inicio_real":"00:30","inicio_no_horario":"NO HORÁRIO","observacoes":"","minutos_atrasado_no_inicio":"","minutos_adiantado_no_inicio":"","horario_saida_da_garagem":"00:20","saiu_no_horario":"SIM","data_iso":"2026-06-21"}],"atualizadoEm":"2026-06-25T22:07:29.457Z"}