{"tripName":"Terminal Shopping Catuaí","routeName":"211 - Patrimônio Regina","shape":"zn{mC`rswH}@a@a@Qa@OmAk@e@Ui@U{@Y[K[G_@ImCOq@?m@@o@?uCNkAHgAFkCJaFHqDSyAIm@Cg@E_DSoAIe@Ea@Cy@?u@?aDTmHn@uCVqCVyNjAaB?k@Ec@G_B]qFcBgFcBgDmAcEgBsCeAi@SkCoAwA{@k@c@]a@]}@Oe@Oc@m@cCUeAU}@cAyD[oAUw@WaAKc@Kc@U_AMi@Mg@Oa@M_@Yg@[c@WWWYm@Yi@Sg@Me@KWGUGeD]sCa@qCc@eBQgAG_AAm@Du@JwAT{Ch@g@Da@Fm@Ao@A[G_@KwAe@m@Qi@S]Ka@OgAaBc@o@QWSYmBmCe@]_@Uc@YYMk@Qo@OqEo@YEkAQiAWa@Mm@Yo@[w@c@{@u@a@]a@_@q@u@i@q@g@o@KMMQkBmCu@eAo@_AsDoFS[EM_@a@A_@CSIMIQOMQC@KCKQYi@y@]k@g@cAWk@Ue@_@y@]y@Sk@k@eBo@gBk@uAo@uAYa@]a@aA{@eDoBcEsB_Bu@QEwBuAiEmC}@e@uB{@g@[g@[mA_AsC_DmAuAk@m@Y[Y[qF_GmAw@}B_AoCu@kAYc@Mc@KeASi@KYGm@[[OWKEGCEAGAICIEIEEACIEICGAM?I?MBIBKJaA@k@Ag@Ga@IoAWg@KYKSQm@g@Y[YYMKAO@q@Do@LcCJgBLw@Nk@Nq@BEDE@EDKDS@K@I?I@CFEJGDIDIFOH[lAsDpCqIH]?MeJKuDGiAAc@A_@Ay@?w@CcCAo@?m@?eBCa@AIhIAjCMTEZ","tzOffset":-3,"price":null,"stops":[{"stopId":153122,"lat":-23.4111842,"lng":-51.2234816,"name":"Patrimônio Regina, 500","int":0,"wait":0},{"stopId":154000,"lat":-23.4097359,"lng":-51.2227249,"name":"PR-538, 500","int":31,"wait":0},{"stopId":153999,"lat":-23.4078208,"lng":-51.2223521,"name":"PR-538, 500","int":68,"wait":0},{"stopId":153997,"lat":-23.4024646,"lng":-51.2224272,"name":"Rodovia Nabio Gonçalves Palhano","int":171,"wait":0},{"stopId":499249,"lat":-23.38737191,"lng":-51.22053062,"name":"PR-538","int":470,"wait":0},{"stopId":153992,"lat":-23.3856117,"lng":-51.2185326,"name":"Rodovia Nabio Gonçalves Palhano","int":521,"wait":0},{"stopId":153991,"lat":-23.3846564,"lng":-51.2155983,"name":"Rodovia Nabio Gonçalves Palhano","int":576,"wait":0},{"stopId":153989,"lat":-23.3826968,"lng":-51.2132514,"name":"Rodovia Nabio Gonçalves Palhano","int":634,"wait":0},{"stopId":153987,"lat":-23.3789767,"lng":-51.2124977,"name":"Rodovia Mabio Gonçalves Palhano, 5620","int":706,"wait":0},{"stopId":499219,"lat":-23.375213,"lng":-51.212477,"name":"PR-538","int":781,"wait":0},{"stopId":153983,"lat":-23.3725064,"lng":-51.2099898,"name":"Rodovia Mabio Gonçalves Palhano, 5520","int":850,"wait":0},{"stopId":153982,"lat":-23.3696897,"lng":-51.20901074,"name":"Rodovia Mabio Gonçalves Palhano, 421","int":908,"wait":0},{"stopId":153979,"lat":-23.3684069,"lng":-51.2076643,"name":"Rodovia Mabio Gonçalves Palhano","int":942,"wait":0},{"stopId":153977,"lat":-23.3661836,"lng":-51.2048185,"name":"Rodovia Mabio Gonçalves Palhano","int":1008,"wait":0},{"stopId":499234,"lat":-23.36524645,"lng":-51.20327891,"name":"Rodovia Mabio Gonçalves Palhano, 3400","int":1042,"wait":0},{"stopId":153974,"lat":-23.3631205,"lng":-51.1993682,"name":"Rodovia Mabio Gonçalves Palhano","int":1122,"wait":0},{"stopId":153972,"lat":-23.3612171,"lng":-51.1981666,"name":"Rodovia Mabio Gonçalves Palhano","int":1164,"wait":0},{"stopId":153969,"lat":-23.35468439,"lng":-51.19278612,"name":"Rodovia Mabio Gonçalves Palhano, 1730","int":1322,"wait":0},{"stopId":396642,"lat":-23.34788077,"lng":-51.18872512,"name":"Rua Carlota Ilnicki","int":1487,"wait":0},{"stopId":208408,"lat":-23.34870458,"lng":-51.18615306,"name":"Rua Carlota Ilnicki, 411-559","int":1536,"wait":0},{"stopId":208407,"lat":-23.34582175,"lng":-51.18342519,"name":"Rua Paulo César Fraga Abelha, 183-449","int":1581,"wait":0},{"stopId":153066,"lat":-23.34382343,"lng":-51.18601963,"name":"Terminal Shopping Catuaí","int":1663,"wait":0}]}