{"tripName":"Terminal Central","routeName":"408 - Vila Recreio","shape":"xkdmCngiwHz@?X?xC?lDBLBJDMs@O_BA_BLyBd@_DNgAnAkIX}BJyAQsDYoDKoAdA?bD@|A?|J?nECxKElDBxC?dL?bGAjA@RA`E?AaHaB@?uD","tzOffset":-3,"price":null,"stops":[{"stopId":208309,"lat":-23.29359604,"lng":-51.17069813,"name":"Rua Padre Manoel da Nóbrega, 28","int":13,"wait":0},{"stopId":155027,"lat":-23.29503855,"lng":-51.16992965,"name":"Rua Tietê, 1526","int":56,"wait":0},{"stopId":155028,"lat":-23.29533619,"lng":-51.1677883,"name":"Rua Tietê, 1327-1373","int":94,"wait":0},{"stopId":153189,"lat":-23.29577777,"lng":-51.1659593,"name":"Rua Iguaçu, 403","int":127,"wait":0},{"stopId":155030,"lat":-23.29571738,"lng":-51.16310136,"name":"Rua Tietê, 939","int":177,"wait":0},{"stopId":153521,"lat":-23.29691031,"lng":-51.16284999,"name":"Rua Guaporé, 1191","int":207,"wait":0},{"stopId":153522,"lat":-23.29980046,"lng":-51.1628384,"name":"Rua Guaporé, 859","int":262,"wait":0},{"stopId":153523,"lat":-23.30156456,"lng":-51.16284424,"name":"Rua Guaporé, 683","int":296,"wait":0},{"stopId":153524,"lat":-23.30298602,"lng":-51.162832,"name":"Rua Guaporé, 510","int":323,"wait":0},{"stopId":153525,"lat":-23.30591889,"lng":-51.16282112,"name":"Rua Guaporé, 193","int":379,"wait":0},{"stopId":15121350,"lat":-23.30825979,"lng":-51.16041072,"name":"Plataforma G - 408","int":484,"wait":0}]}